eda_ji-0.3.2.dist-info/METADATA
eda_ji-0.3.2.dist-info/WHEEL
eda_ji-0.3.2.dist-info/entry_points.txt
eda_ji/__init__.py
eda_ji/cli.py
eda_ji-0.3.2.dist-info/RECORD
