Metadata-Version: 2.1
Name: eda-ji
Version: 0.3.2
Summary: Default template for PDM package
Author-Email: "<jiwon1118>" <<b23386585@gmail.com>>
License: MIT
Requires-Python: >=3.10
Requires-Dist: pandas>=2.2.3
Requires-Dist: president-speech>=0.9.1
Requires-Dist: typer>=0.15.1
